spreg_satosa_sync/__init__.py
spreg_satosa_sync/spreg_satosa_sync.py
spreg_satosa_sync-2.1.2.dist-info/LICENSE
spreg_satosa_sync-2.1.2.dist-info/METADATA
spreg_satosa_sync-2.1.2.dist-info/WHEEL
spreg_satosa_sync-2.1.2.dist-info/entry_points.txt
spreg_satosa_sync-2.1.2.dist-info/top_level.txt
spreg_satosa_sync-2.1.2.dist-info/RECORD
