Metadata-Version: 2.1
Name: spreg-satosa-sync
Version: 2.1.2
Summary: Script to sync SATOSA clients from Perun RPC to mongoDB
Home-page: https://gitlab.ics.muni.cz/perun-proxy-aai/python/spreg-satosa-sync.git
License: UNKNOWN
Platform: UNKNOWN
Requires-Python: >=3.6.2
Requires-Dist: PyYAML (~=6.0)
Requires-Dist: perun.connector (~=3.4)
Requires-Dist: pycryptodomex (~=3.11)
Requires-Dist: pymongo (<5,>=3.12.1)
Requires-Dist: requests (~=2.26)
Requires-Dist: setuptools
